enclave_py_sdk/__init__.py
enclave_py_sdk/app.py
enclave_py_sdk/interfaces/__init__.py
enclave_py_sdk/interfaces/__pycache__/__init__.cpython-312.pyc
enclave_py_sdk/test.py
enclave_py_sdk-0.1.8.dist-info/METADATA
enclave_py_sdk-0.1.8.dist-info/WHEEL
enclave_py_sdk-0.1.8.dist-info/RECORD
